hexdec/__init__.py
hexdec/main.py
hexdec-0.0.1.dist-info/licenses/LICENSE.txt
hexdec-0.0.1.dist-info/METADATA
hexdec-0.0.1.dist-info/WHEEL
hexdec-0.0.1.dist-info/top_level.txt
hexdec-0.0.1.dist-info/RECORD
