Metadata-Version: 2.4
Name: hexdec
Version: 0.0.1
Summary: hexdec library for Python
Author: genahex
Author-email: combtmp+mnr9s@gmail.com
License: MIT
Project-URL: Source Repository, https://github.com
License-File: LICENSE.txt
Requires-Dist: requests
Dynamic: author
Dynamic: author-email
Dynamic: description
Dynamic: description-content-type
Dynamic: license
Dynamic: license-file
Dynamic: project-url
Dynamic: requires-dist
Dynamic: summary
